tilechips/__init__.py
tilechips/tiles.py
tilechips-0.0.2.dist-info/LICENSE
tilechips-0.0.2.dist-info/METADATA
tilechips-0.0.2.dist-info/WHEEL
tilechips-0.0.2.dist-info/top_level.txt
tilechips-0.0.2.dist-info/RECORD
