Metadata-Version: 2.1
Name: tilechips
Version: 0.0.2
Summary: A python package to create raster tiles for deep learning training image chips
Home-page: https://github.com/wslerry/tilechips
Author: Lerry William
Author-email: lerryws.xyz@outlook.com
License: BSD
Keywords: raster gdal
Platform: UNKNOWN
Classifier: Development Status :: 1 - Planning
Classifier: Intended Audience :: Science/Research
Classifier: License :: OSI Approved :: BSD License
Classifier: Operating System :: OS Independent
Classifier: Programming Language :: Python :: 3
Classifier: Programming Language :: Python :: 3.4
Classifier: Programming Language :: Python :: 3.5
Classifier: Programming Language :: Python :: 3.6
Classifier: Programming Language :: Python :: 3.7
Classifier: Programming Language :: Python :: 3.8
Classifier: Programming Language :: Python :: 3.9
Classifier: Topic :: Scientific/Engineering :: GIS
Requires-Dist: GDAL
Requires-Dist: tqdm
